robloxextra/__init__.py
robloxextra-0.8.dist-info/METADATA
robloxextra-0.8.dist-info/WHEEL
robloxextra-0.8.dist-info/top_level.txt
robloxextra-0.8.dist-info/RECORD
