Metadata-Version: 2.4
Name: RobloxExtra
Version: 0.8
Summary: Roblox API Function Wrapper
Home-page: https://github.com/yourname/yourlib
Author: Carter
Author-email: carter@email.com
Classifier: Programming Language :: Python :: 3
Requires-Python: >=3.6
Requires-Dist: requests==2.28.1
Requires-Dist: mss==7.0.1
Requires-Dist: Flask==2.2.2
Requires-Dist: pycryptodome
Dynamic: author
Dynamic: author-email
Dynamic: classifier
Dynamic: description
Dynamic: description-content-type
Dynamic: home-page
Dynamic: requires-dist
Dynamic: requires-python
Dynamic: summary
